aether_utils/__init__.py
aether_utils/argparse_utils.py
aether_utils/jsonl_file_utils.py
aether_utils/jsonl_utils.py
aether_utils/jsonl_utils_async.py
aether_utils/jsonl_utils_multiprocessing.py
aether_utils/jsonl_utils_parallel.py
aether_utils/logging_utils.py
aether_utils-0.0.1.dev2.dist-info/METADATA
aether_utils-0.0.1.dev2.dist-info/WHEEL
aether_utils-0.0.1.dev2.dist-info/licenses/LICENSE
aether_utils-0.0.1.dev2.dist-info/RECORD
